graphenv/__init__.py
graphenv/_version.py
graphenv/graph_env.py
graphenv/graph_model.py
graphenv/graph_model_bellman_mixin.py
graphenv/vertex.py
graphenv/examples/__init__.py
graphenv/examples/hallway/__init__.py
graphenv/examples/hallway/hallway_model.py
graphenv/examples/hallway/hallway_model_torch.py
graphenv/examples/hallway/hallway_state.py
graphenv/examples/tsp/__init__.py
graphenv/examples/tsp/graph_utils.py
graphenv/examples/tsp/tsp_model.py
graphenv/examples/tsp/tsp_nfp_model.py
graphenv/examples/tsp/tsp_nfp_state.py
graphenv/examples/tsp/tsp_preprocessor.py
graphenv/examples/tsp/tsp_state.py
tests/__init__.py
tests/conftest.py
tests/test_graph_model_utils.py
tests/test_hallway.py
tests/test_tsp.py
graphenv-0.2.6.dist-info/LICENSE
graphenv-0.2.6.dist-info/METADATA
graphenv-0.2.6.dist-info/WHEEL
graphenv-0.2.6.dist-info/top_level.txt
graphenv-0.2.6.dist-info/RECORD
