Metadata-Version: 2.1
Name: graphenv
Version: 0.2.6
Summary: Reinforcement learning on directed graphs
License: BSD 3-Clause License
Classifier: License :: OSI Approved :: BSD License
Classifier: Programming Language :: Python :: 3
License-File: LICENSE
Requires-Dist: networkx (==3.0)
Requires-Dist: ray[rllib,tune] (==2.3.1)
Requires-Dist: tensorboardX (==2.6.0)
Requires-Dist: numpy (<1.24.0)
Requires-Dist: tqdm (==4.64.1)
Requires-Dist: matplotlib
Provides-Extra: dev
Requires-Dist: torch ; extra == 'dev'
Requires-Dist: tensorflow ; extra == 'dev'
Requires-Dist: pytest ; extra == 'dev'
Provides-Extra: tensorflow
Requires-Dist: tensorflow ; extra == 'tensorflow'
Provides-Extra: torch
Requires-Dist: torch ; extra == 'torch'
